photoshop/__init__.py
photoshop/__version__.py
photoshop/api/__init__.py
photoshop/api/_active_layer.py
photoshop/api/_artlayer.py
photoshop/api/_artlayers.py
photoshop/api/_channel.py
photoshop/api/_channels.py
photoshop/api/_core.py
photoshop/api/_document.py
photoshop/api/_documentinfo.py
photoshop/api/_documents.py
photoshop/api/_layerComp.py
photoshop/api/_layerComps.py
photoshop/api/_layerSet.py
photoshop/api/_layerSets.py
photoshop/api/_layers.py
photoshop/api/_measurement_log.py
photoshop/api/_notifier.py
photoshop/api/_notifiers.py
photoshop/api/_preferences.py
photoshop/api/_selection.py
photoshop/api/_text_fonts.py
photoshop/api/action_descriptor.py
photoshop/api/action_list.py
photoshop/api/action_reference.py
photoshop/api/application.py
photoshop/api/batch_options.py
photoshop/api/colors/__init__.py
photoshop/api/colors/cmyk.py
photoshop/api/colors/gray.py
photoshop/api/colors/hsb.py
photoshop/api/colors/lab.py
photoshop/api/colors/rgb.py
photoshop/api/constants.py
photoshop/api/enumerations.py
photoshop/api/errors.py
photoshop/api/event_id.py
photoshop/api/open_options/__init__.py
photoshop/api/open_options/eps.py
photoshop/api/save_options/__init__.py
photoshop/api/save_options/bmp.py
photoshop/api/save_options/eps.py
photoshop/api/save_options/gif.py
photoshop/api/save_options/jpg.py
photoshop/api/save_options/pdf.py
photoshop/api/save_options/png.py
photoshop/api/save_options/psd.py
photoshop/api/save_options/tag.py
photoshop/api/save_options/tif.py
photoshop/api/solid_color.py
photoshop/api/text_font.py
photoshop/api/text_item.py
photoshop/session.py
photoshop_python_api-0.24.1.dist-info/LICENSE
photoshop_python_api-0.24.1.dist-info/METADATA
photoshop_python_api-0.24.1.dist-info/WHEEL
photoshop_python_api-0.24.1.dist-info/RECORD
