Metadata-Version: 2.3
Name: photoshop-python-api
Version: 0.24.1
Summary: Python API for Photoshop.
License: MIT
Keywords: python-api, photoshop-python-api,photoshop,python
Author: longhao
Author-email: hal.long@outlook.com
Requires-Python: >=3.8,<4.0
Classifier: Development Status :: 4 - Beta
Classifier: License :: OSI Approved :: MIT License
Classifier: Operating System :: Microsoft :: Windows
Classifier: Operating System :: Microsoft :: Windows :: Windows 10
Classifier: Programming Language :: Python :: 3
Classifier: Programming Language :: Python :: 3.8
Classifier: Programming Language :: Python :: 3.9
Classifier: Programming Language :: Python :: 3.10
Classifier: Programming Language :: Python :: 3.11
Classifier: Programming Language :: Python :: 3.12
Classifier: Programming Language :: Python :: 3.13
Classifier: Programming Language :: Python :: 3 :: Only
Requires-Dist: comtypes (>=1.1.11,<2.0.0)
Requires-Dist: wheel (>=0.45.0,<0.46.0)
Project-URL: Documentation, https://photoshop-python-api.readthedocs.io/en/master/
Project-URL: Homepage, https://github.com/loonghao/photoshop-python-api
Project-URL: Repository, https://github.com/loonghao/photoshop-python-api
